[
  {
    "timestamp": "2025-03-13T18:50:20.595Z",
    "data": "Humidity: 64.00 %\tTemperature: 23.60 C"
  },
  {
    "timestamp": "2025-03-13T18:50:22.676Z",
    "data": "Humidity: 64.00 %\tTemperature: 23.60 C"
  },
  {
    "timestamp": "2025-03-13T18:50:24.752Z",
    "data": "Humidity: 64.00 %\tTemperature: 23.60 C"
  },
  {
    "timestamp": "2025-03-13T18:50:26.829Z",
    "data": "Humidity: 64.00 %\tTemperature: 23.60 C"
  },
  {
    "timestamp": "2025-03-13T18:50:28.909Z",
    "data": "Humidity: 64.00 %\tTemperature: 23.60 C"
  },
  {
    "timestamp": "2025-03-13T18:50:30.986Z",
    "data": "Humidity: 64.00 %\tTemperature: 23.60 C"
  },
  {
    "timestamp": "2025-03-13T18:50:33.067Z",
    "data": "Humidity: 64.00 %\tTemperature: 23.60 C"
  },
  {
    "timestamp": "2025-03-13T18:50:35.144Z",
    "data": "Humidity: 64.00 %\tTemperature: 23.60 C"
  },
  {
    "timestamp": "2025-03-13T18:50:37.335Z",
    "data": "Humidity: 64.00 %\tTemperature: 23.60 C"
  },
  {
    "timestamp": "2025-03-13T18:50:39.301Z",
    "data": "Humidity: 64.00 %\tTemperature: 23.60 C"
  },
  {
    "timestamp": "2025-03-13T18:50:41.377Z",
    "data": "Humidity: 64.00 %\tTemperature: 23.60 C"
  },
  {
    "timestamp": "2025-03-13T18:50:43.454Z",
    "data": "Humidity: 64.00 %\tTemperature: 23.60 C"
  },
  {
    "timestamp": "2025-03-13T18:50:45.535Z",
    "data": "Humidity: 64.00 %\tTemperature: 23.60 C"
  },
  {
    "timestamp": "2025-03-13T18:50:47.611Z",
    "data": "Humidity: 64.00 %\tTemperature: 23.60 C"
  },
  {
    "timestamp": "2025-03-13T18:50:49.692Z",
    "data": "Humidity: 64.00 %\tTemperature: 23.60 C"
  },
  {
    "timestamp": "2025-03-13T18:50:51.769Z",
    "data": "Humidity: 64.00 %\tTemperature: 23.60 C"
  },
  {
    "timestamp": "2025-03-13T18:50:53.845Z",
    "data": "Humidity: 64.00 %\tTemperature: 23.60 C"
  },
  {
    "timestamp": "2025-03-13T18:50:55.926Z",
    "data": "Humidity: 64.00 %\tTemperature: 23.60 C"
  },
  {
    "timestamp": "2025-03-13T18:50:58.003Z",
    "data": "Humidity: 64.00 %\tTemperature: 23.60 C"
  },
  {
    "timestamp": "2025-03-13T18:51:00.080Z",
    "data": "Humidity: 64.00 %\tTemperature: 23.60 C"
  },
  {
    "timestamp": "2025-03-13T18:51:02.160Z",
    "data": "Humidity: 64.00 %\tTemperature: 23.60 C"
  },
  {
    "timestamp": "2025-03-13T18:51:04.237Z",
    "data": "Humidity: 64.00 %\tTemperature: 23.60 C"
  },
  {
    "timestamp": "2025-03-13T18:51:06.318Z",
    "data": "Humidity: 64.00 %\tTemperature: 23.60 C"
  },
  {
    "timestamp": "2025-03-13T18:51:08.395Z",
    "data": "Humidity: 64.00 %\tTemperature: 23.60 C"
  },
  {
    "timestamp": "2025-03-13T18:51:10.471Z",
    "data": "Humidity: 64.00 %\tTemperature: 23.60 C"
  },
  {
    "timestamp": "2025-03-13T18:51:12.552Z",
    "data": "Humidity: 64.00 %\tTemperature: 23.60 C"
  },
  {
    "timestamp": "2025-03-13T18:51:14.629Z",
    "data": "Humidity: 64.00 %\tTemperature: 23.60 C"
  },
  {
    "timestamp": "2025-03-13T18:51:16.705Z",
    "data": "Humidity: 64.00 %\tTemperature: 23.60 C"
  },
  {
    "timestamp": "2025-03-13T18:51:18.787Z",
    "data": "Humidity: 64.00 %\tTemperature: 23.60 C"
  },
  {
    "timestamp": "2025-03-13T18:51:20.867Z",
    "data": "Humidity: 64.00 %\tTemperature: 23.60 C"
  }
]